{
    "description": "Schema for Product Search Result Entity",
    "properties": {
      "name": {
        "type": "string",
        "minLength": 1
      },
      "url": {
        "type": "string",
        "minLength": 1
      },
      "rank": {
        "type": "number"
      },
      "sku": {
        "type": "string",
        "minLength": 1
      },
      "imageUrl": {
        "type": "string",
        "minLength": 1
      },
      "price": {
        "type": "number"
      }
    },
    "additionalProperties": false,
    "type": "object",
    "required": [
      "name",
      "url",
      "rank",
      "sku",
      "imageUrl"
    ],
    "self": {
      "vendor": "com.adobe.magento.entity",
      "name": "search-result-product",
      "format": "jsonschema",
      "version": "1-0-3"
    },
    "$schema": "http://iglucentral.com/schemas/com.snowplowanalytics.self-desc/schema/jsonschema/1-0-0#"
  }
